langchain_oceanbase/__init__.py
langchain_oceanbase/ai_functions.py
langchain_oceanbase/chat_message_histories.py
langchain_oceanbase/client_utils.py
langchain_oceanbase/embedding_utils.py
langchain_oceanbase/py.typed
langchain_oceanbase/vectorstores.py
langchain_oceanbase-0.3.2.dist-info/METADATA
langchain_oceanbase-0.3.2.dist-info/WHEEL
langchain_oceanbase-0.3.2.dist-info/licenses/LICENSE
langchain_oceanbase-0.3.2.dist-info/RECORD
