Metadata-Version: 2.4
Name: langchain-oceanbase
Version: 0.3.2
Summary: An integration package connecting OceanBase and LangChain
License: MIT
License-File: LICENSE
Author: shanhaikang.shk
Author-email: shanhaikang.shk@oceanbase.com
Requires-Python: >=3.11,<4.0
Classifier: License :: OSI Approved :: MIT License
Classifier: Programming Language :: Python :: 3
Classifier: Programming Language :: Python :: 3.11
Classifier: Programming Language :: Python :: 3.12
Classifier: Programming Language :: Python :: 3.13
Classifier: Programming Language :: Python :: 3.14
Requires-Dist: langchain-core (>=1.0.0)
Requires-Dist: pyobvector (>=0.2.0)
Requires-Dist: pyseekdb (>=0.1.0)
Project-URL: Release Notes, https://github.com/langchain-ai/langchain/releases?q=tag%3A%22oceanbase%3D%3D0%22&expanded=true
Project-URL: Source Code, https://github.com/langchain-ai/langchain/tree/master/libs/partners/oceanbase
